ecube/__init__.py
ecube/ecube_hooks.py
ecube/environments.py
ecube/gql.py
ecube/parser.py
ecube/playbook.py
ecube/playbook_create.py
ecube/run.py
ecube/files/template.yml
ecube/gql_operations/Localops.py
ecube/gql_operations/Mutations.py
ecube/gql_operations/Queries.py
ecube/gql_operations/Subscriptions.py
ecube/gql_operations/__init__.py
epiphani_ecube-1.1.0.data/scripts/e3
epiphani_ecube-1.1.0.dist-info/LICENSE
epiphani_ecube-1.1.0.dist-info/METADATA
epiphani_ecube-1.1.0.dist-info/WHEEL
epiphani_ecube-1.1.0.dist-info/top_level.txt
epiphani_ecube-1.1.0.dist-info/RECORD
