Metadata-Version: 2.1
Name: epiphani-ecube
Version: 1.1.0
Summary: epiphani CLI for registering connectors & executing scripts in a sandbox
Home-page: https://github.com/epiphani-inc/ecube
Author: Praveen Madhav
Author-email: praveen@epiphani.io
License: MIT
Platform: UNKNOWN
Requires-Python: >=2.7
Requires-Dist: tabulate
Requires-Dist: PyYAML
Requires-Dist: Jinja2
Requires-Dist: websocket-client (>=0.57.0)
Requires-Dist: warrant (>=0.6.1)
Requires-Dist: configparser
Requires-Dist: requests
Requires-Dist: epiphani-appsync-subscription-manager (>=0.1.0)
